{
  "title": "An application-based taxonomy for brain-computer interfaces",
  "authors": [
    "Jacob T. Robinson",
    "Sumner L. Norman",
    "Matthew R. Angle",
    "Timothy G. Constandinou",
    "Timothy Denison",
    "John P. Donoghue",
    "Ryan M. Field",
    "Andreas Forsland",
    "Sid Kouider",
    "José del R. Millán",
    "Jonathan A. Michaels",
    "Amy L. Orsborn",
    "Chethan Pandarinath",
    "J. Andrew Pruszynski",
    "Christopher J. Rozell",
    "Nishal P. Shah",
    "Maryam M. Shanechi",
    "Mahsa Shoaran",
    "Sameer A. Sheth",
    "Sergey D. Stavisky",
    "Eric Trautmann",
    "Nicolas Vachicouras",
    "Chong Xie"
  ],
  "year": 2024,
  "publication": "Nature Biomedical Engineering",
  "abstract": "Naming brain-computer interfaces according to their intended application will assist stakeholders in the evaluation of the benefits and risks of neurotechnologies. This paper proposes a taxonomy to align BCI terminology with public understanding, aiming to assist regulators, healthcare providers, patients, and other stakeholders in navigating the BCI landscape more clearly.",
  "keywords": [
    "brain-computer interface",
    "taxonomy",
    "neurotechnology",
    "regulation",
    "stakeholders",
    "BCI classification",
    "neuroethics"
  ],
  "doi": "10.1038/s41551-024-01326-z",
  "pdf": "",
  "code": "",
  "bibtex": "@article{robinson2024,\n  title={An application-based taxonomy for brain-computer interfaces},\n  author={Robinson, Jacob T. and Norman, Sumner L. and Angle, Matthew R. and Constandinou, Timothy G. and Denison, Timothy and Donoghue, John P. and Field, Ryan M. and Forsland, Andreas and Kouider, Sid and Millán, José del R. and Michaels, Jonathan A. and Orsborn, Amy L. and Pandarinath, Chethan and Pruszynski, J. Andrew and Rozell, Christopher J. and Shah, Nishal P. and Shanechi, Maryam M. and Shoaran, Mahsa and Sheth, Sameer A. and Stavisky, Sergey D. and Trautmann, Eric and Vachicouras, Nicolas and Xie, Chong},\n  journal={Nature Biomedical Engineering},\n  year={2024},\n  doi={10.1038/s41551-024-01326-z},\n  publisher={Nature Publishing Group}\n}",
  "citations": 0,
  "added_date": "2025-06-06",
  "volume": "",
  "pages": "",
  "url": "https://www.nature.com/articles/s41551-024-01326-z"
}